pyscsopt/__init__.py
pyscsopt/problems.py
pyscsopt/algorithms/__init__.py
pyscsopt/algorithms/iterate.py
pyscsopt/algorithms/prox_ggn_score.py
pyscsopt/algorithms/prox_l_bfgs_score.py
pyscsopt/algorithms/prox_n_score.py
pyscsopt/media/__init__.py
pyscsopt/prox/__init__.py
pyscsopt/prox/prox_operators.py
pyscsopt/regularizers/__init__.py
pyscsopt/regularizers/exponential_smooth.py
pyscsopt/regularizers/log_exp_smooth.py
pyscsopt/regularizers/phuber_smooth.py
pyscsopt/regularizers/regularizers.py
pyscsopt/regularizers/smoothing.py
pyscsopt/test/__init__.py
pyscsopt/test/test_algs.py
pyscsopt/test/test_smooth.py
pyscsopt/utils/__init__.py
pyscsopt/utils/prox_reg_utils.py
pyscsopt/utils/utils.py
pyscsopt-0.1.52.dist-info/licenses/LICENSE
pyscsopt-0.1.52.dist-info/METADATA
pyscsopt-0.1.52.dist-info/WHEEL
pyscsopt-0.1.52.dist-info/top_level.txt
pyscsopt-0.1.52.dist-info/RECORD
