Metadata-Version: 2.4
Name: pyscsopt
Version: 0.1.52
Summary: A Python library for self-concordant smooth optimization (Python port of SelfConcordantSmoothOptimization.jl)
Home-page: https://github.com/adeyemiadeoye/pyscsopt
Author: Adeyemi Damilare Adeoye
Author-email: 
Classifier: Development Status :: 5 - Production/Stable
Classifier: Intended Audience :: Science/Research
Classifier: Operating System :: OS Independent
Classifier: Topic :: Scientific/Engineering
Classifier: License :: OSI Approved :: Apache Software License
Classifier: Programming Language :: Python :: 3
Requires-Python: >=3.8
License-File: LICENSE
Requires-Dist: numpy
Requires-Dist: scipy
Requires-Dist: jax
Dynamic: home-page
Dynamic: license-file
Dynamic: requires-python
